azure/mgmt/appconfiguration/__init__.py
azure/mgmt/appconfiguration/_app_configuration_management_client.py
azure/mgmt/appconfiguration/_configuration.py
azure/mgmt/appconfiguration/_patch.py
azure/mgmt/appconfiguration/_serialization.py
azure/mgmt/appconfiguration/_version.py
azure/mgmt/appconfiguration/py.typed
azure/mgmt/appconfiguration/aio/__init__.py
azure/mgmt/appconfiguration/aio/_app_configuration_management_client.py
azure/mgmt/appconfiguration/aio/_configuration.py
azure/mgmt/appconfiguration/aio/_patch.py
azure/mgmt/appconfiguration/aio/operations/__init__.py
azure/mgmt/appconfiguration/aio/operations/_configuration_stores_operations.py
azure/mgmt/appconfiguration/aio/operations/_key_values_operations.py
azure/mgmt/appconfiguration/aio/operations/_operations.py
azure/mgmt/appconfiguration/aio/operations/_patch.py
azure/mgmt/appconfiguration/aio/operations/_private_endpoint_connections_operations.py
azure/mgmt/appconfiguration/aio/operations/_private_link_resources_operations.py
azure/mgmt/appconfiguration/aio/operations/_replicas_operations.py
azure/mgmt/appconfiguration/aio/operations/_snapshots_operations.py
azure/mgmt/appconfiguration/models/__init__.py
azure/mgmt/appconfiguration/models/_app_configuration_management_client_enums.py
azure/mgmt/appconfiguration/models/_models_py3.py
azure/mgmt/appconfiguration/models/_patch.py
azure/mgmt/appconfiguration/operations/__init__.py
azure/mgmt/appconfiguration/operations/_configuration_stores_operations.py
azure/mgmt/appconfiguration/operations/_key_values_operations.py
azure/mgmt/appconfiguration/operations/_operations.py
azure/mgmt/appconfiguration/operations/_patch.py
azure/mgmt/appconfiguration/operations/_private_endpoint_connections_operations.py
azure/mgmt/appconfiguration/operations/_private_link_resources_operations.py
azure/mgmt/appconfiguration/operations/_replicas_operations.py
azure/mgmt/appconfiguration/operations/_snapshots_operations.py
azure_mgmt_appconfiguration-4.0.0.dist-info/LICENSE
azure_mgmt_appconfiguration-4.0.0.dist-info/METADATA
azure_mgmt_appconfiguration-4.0.0.dist-info/WHEEL
azure_mgmt_appconfiguration-4.0.0.dist-info/top_level.txt
azure_mgmt_appconfiguration-4.0.0.dist-info/RECORD
